abate/__init__.py
abate/fit_GENERIC.py
abate/simple_pymc_fits.py
abate-0.0.dev7.dist-info/LICENSE.rtf
abate-0.0.dev7.dist-info/METADATA
abate-0.0.dev7.dist-info/WHEEL
abate-0.0.dev7.dist-info/top_level.txt
abate-0.0.dev7.dist-info/RECORD
